edc_subject_model_wrappers/__init__.py
edc_subject_model_wrappers/appointment_model_wrapper.py
edc_subject_model_wrappers/apps.py
edc_subject_model_wrappers/crf_model_wrapper.py
edc_subject_model_wrappers/requisition_model_wrapper.py
edc_subject_model_wrappers/subject_consent_model_wrapper.py
edc_subject_model_wrappers/subject_locator_model_wrapper.py
edc_subject_model_wrappers/subject_visit_model_wrapper.py
edc_subject_model_wrappers/tests/__init__.py
edc_subject_model_wrappers/tests/admin.py
edc_subject_model_wrappers/tests/models.py
edc_subject_model_wrappers/tests/urls.py
edc_subject_model_wrappers/tests/visit_schedule.py
edc_subject_model_wrappers/tests/tests/__init__.py
edc_subject_model_wrappers/tests/tests/test_appointment_model_wrapper.py
edc_subject_model_wrappers/tests/tests/test_subject_visit_model_wrapper.py
edc_subject_model_wrapper-0.1.0.dist-info/LICENSE
edc_subject_model_wrapper-0.1.0.dist-info/METADATA
edc_subject_model_wrapper-0.1.0.dist-info/WHEEL
edc_subject_model_wrapper-0.1.0.dist-info/top_level.txt
edc_subject_model_wrapper-0.1.0.dist-info/RECORD
