Metadata-Version: 2.1
Name: edc-subject-model-wrapper
Version: 0.1.0
Summary: Subject Model wrappers for clinicedc/edc projects
Home-page: http://github.com/clinicedc/edc-subject-model-wrapper
Author: Erik van Widenfelt
Author-email: ew2789@gmail.com
License: GPL license, see LICENSE
Keywords: django Edc model wrapper dashboard classes and templates
Platform: UNKNOWN
Classifier: Environment :: Web Environment
Classifier: Framework :: Django
Classifier: Intended Audience :: Developers
Classifier: Intended Audience :: Science/Research
Classifier: License :: OSI Approved :: GNU General Public License v3 (GPLv3)
Classifier: Operating System :: OS Independent
Classifier: Programming Language :: Python :: 3.7
Classifier: Topic :: Internet :: WWW/HTTP
Classifier: Topic :: Internet :: WWW/HTTP :: Dynamic Content
Requires-Python: >=3.7
Requires-Dist: edc-model-wrapper
Requires-Dist: edc-visit-schedule
Requires-Dist: edc-notification
Requires-Dist: edc-metadata
Requires-Dist: edc-locator
